odoo/addons/website_forum_subscription/README.rst
odoo/addons/website_forum_subscription/__init__.py
odoo/addons/website_forum_subscription/__manifest__.py
odoo/addons/website_forum_subscription/i18n/es.po
odoo/addons/website_forum_subscription/i18n/it.po
odoo/addons/website_forum_subscription/i18n/website_forum_subscription.pot
odoo/addons/website_forum_subscription/readme/CONTRIBUTORS.rst
odoo/addons/website_forum_subscription/readme/DESCRIPTION.rst
odoo/addons/website_forum_subscription/readme/USAGE.rst
odoo/addons/website_forum_subscription/static/description/icon.png
odoo/addons/website_forum_subscription/static/description/index.html
odoo/addons/website_forum_subscription/templates/website_forum_templates.xml
odoo14_addon_website_forum_subscription-14.0.1.0.1.dev6.dist-info/METADATA
odoo14_addon_website_forum_subscription-14.0.1.0.1.dev6.dist-info/WHEEL
odoo14_addon_website_forum_subscription-14.0.1.0.1.dev6.dist-info/top_level.txt
odoo14_addon_website_forum_subscription-14.0.1.0.1.dev6.dist-info/RECORD
